{"cameraMode":{"drawMode":0,"name":"Shaded","section":"Shading Mode"},"sceneLighting":true,"audioPlay":false,"sceneViewState":{"showFog":true,"showMaterialUpdate":false,"showSkybox":true,"showFlares":true,"showImageEffects":true,"showParticleSystems":true},"in2DMode":false,"pivot":{"x":27.85146141052246,"y":-1.3797003030776978,"z":14.674846649169922},"rotation":{"x":-0.10757432132959366,"y":0.8910796642303467,"z":-0.28475961089134219,"w":-0.33662572503089907},"size":159.1656494140625,"orthographic":false}